Metadata-Version: 1.0
Name: modada
Version: 0.1
Summary: the tiny game about legend of modada
Home-page: UNKNOWN
Author: Aaron
Author-email: shuju891@163.com
License: UNKNOWN
Platform: UNKNOWN
